avantpy/__init__.py
avantpy/__main__.py
avantpy/console.py
avantpy/converter.py
avantpy/exception_handling.py
avantpy/exceptions.py
avantpy/gui.py
avantpy/import_hook.py
avantpy/invocation.py
avantpy/my_gettext.py
avantpy/session.py
avantpy/utils.py
avantpy/version.py
avantpy/dialects/__init__.py
avantpy/dialects/pyen.py
avantpy/dialects/pyes.py
avantpy/dialects/pyfr.py
avantpy/dialects/pyupper.py
tests/__init__.py
tests/conftest.py
tests/replicate_tests.py
tests/tb_common.py
tests/tb_pyfr.py
tests/tb_pyupper.py
tests/test_console.py
tests/test_transcoder.py
tests/pyen/__init__.py
tests/pyen/catch_if_nobreak.py
tests/pyen/catch_mismatchedbrackets.py
tests/pyen/catch_missing_leftbracket.py
tests/pyen/catch_missing_repeat.py
tests/pyen/catch_missing_repeat_colon.py
tests/pyen/catch_name_error.py
tests/pyen/catch_nobreak_first.py
tests/pyen/catch_nobreak_syntax.py
tests/pyen/catch_repeat_first.py
tests/pyen/catch_try_nobreak.py
tests/pyen/catch_unknown_dialect.py
tests/pyen/catch_unknown_language.py
tests/pyen/test_pyen.py
tests/pyes/__init__.py
tests/pyes/catch_if_nobreak.py
tests/pyes/catch_mismatchedbrackets.py
tests/pyes/catch_missing_leftbracket.py
tests/pyes/catch_missing_repeat.py
tests/pyes/catch_missing_repeat_colon.py
tests/pyes/catch_name_error.py
tests/pyes/catch_nobreak_first.py
tests/pyes/catch_nobreak_syntax.py
tests/pyes/catch_repeat_first.py
tests/pyes/catch_try_nobreak.py
tests/pyes/catch_unknown_dialect.py
tests/pyes/catch_unknown_language.py
tests/pyes/test_pyes.py
tests/pyfr/__init__.py
tests/pyfr/catch_if_nobreak.py
tests/pyfr/catch_mismatchedbrackets.py
tests/pyfr/catch_missing_leftbracket.py
tests/pyfr/catch_missing_repeat.py
tests/pyfr/catch_missing_repeat_colon.py
tests/pyfr/catch_name_error.py
tests/pyfr/catch_nobreak_first.py
tests/pyfr/catch_nobreak_syntax.py
tests/pyfr/catch_repeat_first.py
tests/pyfr/catch_try_nobreak.py
tests/pyfr/catch_unknown_dialect.py
tests/pyfr/catch_unknown_language.py
tests/pyfr/test_pyfr.py
avantpy-0.0.15.dist-info/LICENSE
avantpy-0.0.15.dist-info/METADATA
avantpy-0.0.15.dist-info/WHEEL
avantpy-0.0.15.dist-info/top_level.txt
avantpy-0.0.15.dist-info/RECORD
