Metadata-Version: 2.1
Name: avantpy
Version: 0.0.15
Summary: Python with training wheels: executable pseudocode in any language.
Home-page: https://github.com/aroberge/avantpy
Author: André Roberge
Author-email: Andre.Roberge@gmail.com
License: UNKNOWN
Platform: UNKNOWN
Classifier: Development Status :: 1 - Planning
Classifier: License :: OSI Approved :: MIT License
Classifier: Programming Language :: Python :: 3
Classifier: Programming Language :: Python :: 3.7
Classifier: Intended Audience :: Education
Classifier: Topic :: Education
Requires-Dist: friendly-traceback
